<?xml version="1.0" encoding="utf-8" ?>
<List>
  <hash>#</hash>   
  <apartment>apt</apartment>
  <apt>apt</apt>
  <basement>bsmt</basement>
  <bsmt>bsmt</bsmt>
  <building>bldg</building>
  <bldg>bldg</bldg>   
  <department>dept</department>
  <dept>dept</dept>
  <floor>fl</floor>
  <fl>fl</fl>
  <front>frnt</front>
  <frnt>frnt</frnt>
  <hanger>hngr</hanger>   
  <hngr>hngr</hngr>
  <key>key</key>
  <key>key</key>
  <lobby>lbby</lobby>
  <lbby>lbby</lbby>
  <lot>lot</lot>
  <lot>lot</lot>
  <lower>lowr</lower>   
  <lowr>lowr</lowr>
  <office>ofc</office>
  <ofc>ofc</ofc>
  <penthouse>ph</penthouse>
  <ph>ph</ph>
  <pier>pier</pier>
  <pier>pier</pier>
  <rear>rear</rear>   
  <rear>rear</rear>
  <room>rm</room>
  <rm>rm</rm>
  <side>side</side>
  <side>side</side>
  <slip>slip</slip>
  <slip>slip</slip>
  <space>spc</space>
  <spc>spc</spc>   
  <stop>stop</stop>
  <stop>stop</stop>
  <suite>ste</suite>
  <ste>ste</ste>
  <trailer>trlr</trailer>
  <trlr>trlr</trlr>
  <unit>unit</unit>
  <unit>unit</unit>   
  <upper>uppr</upper>
  <uppr>uppr</uppr>
</List>
